<?xml version="1.0" encoding="utf-8" ?>
<dwsync>
<file name="active_record.html" server="E:/7153210/" local="130222494687380342" remote="130222494680000000" />
<file name="caching.html" server="E:/7153210/" local="130222494687820609" remote="130222494680000000" />
<file name="call_function.html" server="E:/7153210/" local="130222494688083299" remote="130222494680000000" />
<file name="configuration.html" server="E:/7153210/" local="130222494688346054" remote="130222494680000000" />
<file name="connecting.html" server="E:/7153210/" local="130222494688632078" remote="130222494680000000" />
<file name="examples.html" server="E:/7153210/" local="130222494688925877" remote="130222494680000000" />
<file name="fields.html" server="E:/7153210/" local="130222494689202890" remote="130222494680000000" />
<file name="forge.html" server="E:/7153210/" local="130222494689550152" remote="130222494680000000" />
<file name="helpers.html" server="E:/7153210/" local="130222494689883830" remote="130222494680000000" />
<file name="index.html" server="E:/7153210/" local="130222494690189974" remote="130222494690000000" />
<file name="queries.html" server="E:/7153210/" local="130222494690482652" remote="130222494690000000" />
<file name="results.html" server="E:/7153210/" local="130222494690774526" remote="130222494690000000" />
<file name="table_data.html" server="E:/7153210/" local="130222494691065234" remote="130222494690000000" />
<file name="transactions.html" server="E:/7153210/" local="130222494691341438" remote="130222494690000000" />
<file name="utilities.html" server="E:/7153210/" local="130222494691898149" remote="130222494690000000" />
</dwsync>